feedback/DataFormation.py
feedback/GetData.py
feedback/Scheduler.py
feedback/__init__.py
feedback/applicationScheduler.py
dynamodb_feeds_to_sqs-0.1.1.dist-info/LICENSE.txt
dynamodb_feeds_to_sqs-0.1.1.dist-info/METADATA
dynamodb_feeds_to_sqs-0.1.1.dist-info/WHEEL
dynamodb_feeds_to_sqs-0.1.1.dist-info/top_level.txt
dynamodb_feeds_to_sqs-0.1.1.dist-info/RECORD
